LICENSE
README.md
setup.cfg
setup.py
parallel_wavegan/__init__.py
parallel_wavegan.egg-info/PKG-INFO
parallel_wavegan.egg-info/SOURCES.txt
parallel_wavegan.egg-info/dependency_links.txt
parallel_wavegan.egg-info/entry_points.txt
parallel_wavegan.egg-info/requires.txt
parallel_wavegan.egg-info/top_level.txt
parallel_wavegan/bin/__init__.py
parallel_wavegan/bin/compute_statistics.py
parallel_wavegan/bin/decode.py
parallel_wavegan/bin/evaluate_f0.py
parallel_wavegan/bin/evaluate_mcd.py
parallel_wavegan/bin/normalize.py
parallel_wavegan/bin/preprocess.py
parallel_wavegan/bin/train.py
parallel_wavegan/datasets/__init__.py
parallel_wavegan/datasets/audio_mel_dataset.py
parallel_wavegan/datasets/scp_dataset.py
parallel_wavegan/distributed/__init__.py
parallel_wavegan/distributed/launch.py
parallel_wavegan/functions/__init__.py
parallel_wavegan/functions/vector_quantizer.py
parallel_wavegan/layers/__init__.py
parallel_wavegan/layers/causal_conv.py
parallel_wavegan/layers/duration_predictor.py
parallel_wavegan/layers/layer_norm.py
parallel_wavegan/layers/length_regulator.py
parallel_wavegan/layers/pqmf.py
parallel_wavegan/layers/residual_block.py
parallel_wavegan/layers/residual_stack.py
parallel_wavegan/layers/sine.py
parallel_wavegan/layers/tade_res_block.py
parallel_wavegan/layers/tf_layers.py
parallel_wavegan/layers/upsample.py
parallel_wavegan/layers/variance_predictor.py
parallel_wavegan/layers/vector_quantize_codebook.py
parallel_wavegan/losses/__init__.py
parallel_wavegan/losses/adversarial_loss.py
parallel_wavegan/losses/duration_prediction_loss.py
parallel_wavegan/losses/feat_match_loss.py
parallel_wavegan/losses/mel_loss.py
parallel_wavegan/losses/stft_loss.py
parallel_wavegan/models/__init__.py
parallel_wavegan/models/hifigan.py
parallel_wavegan/models/melgan.py
parallel_wavegan/models/parallel_wavegan.py
parallel_wavegan/models/style_melgan.py
parallel_wavegan/models/tf_models.py
parallel_wavegan/models/uhifigan.py
parallel_wavegan/models/vqvae.py
parallel_wavegan/optimizers/__init__.py
parallel_wavegan/optimizers/radam.py
parallel_wavegan/utils/__init__.py
parallel_wavegan/utils/utils.py
test/test_hifigan.py
test/test_layers.py
test/test_mel_loss.py
test/test_melgan.py
