Metadata-Version: 2.1
Name: parallel-wavegan
Version: 0.6.1
Summary: Parallel WaveGAN implementation
Home-page: http://github.com/kan-bayashi/ParallelWaveGAN
Author: Tomoki Hayashi
Author-email: hayashi.tomoki@g.sp.m.is.nagoya-u.ac.jp
License: MIT License
Platform: UNKNOWN
Classifier: Programming Language :: Python :: 3.8
Classifier: Programming Language :: Python :: 3.9
Classifier: Programming Language :: Python :: 3.10
Classifier: Intended Audience :: Science/Research
Classifier: Operating System :: POSIX :: Linux
Classifier: License :: OSI Approved :: MIT License
Classifier: Topic :: Software Development :: Libraries :: Python Modules
Provides-Extra: test
